cryptoexchanges/__init__.py
cryptoexchanges/admin.py
cryptoexchanges/apps.py
cryptoexchanges/models.py
cryptoexchanges/tests.py
cryptoexchanges/views.py
cryptoexchanges/migrations/__init__.py
cryptoexchanges/providers/__init__.py
cryptoexchanges/providers/base.py
cryptoexchanges/providers/binance/__init__.py
cryptoexchanges/providers/binance/provider.py
cryptoexchanges/providers/gdax/__init__.py
cryptoexchanges/providers/gdax/provider.py
django_crypto_exchanges-0.1.0.dev2.dist-info/DESCRIPTION.rst
django_crypto_exchanges-0.1.0.dev2.dist-info/METADATA
django_crypto_exchanges-0.1.0.dev2.dist-info/RECORD
django_crypto_exchanges-0.1.0.dev2.dist-info/WHEEL
django_crypto_exchanges-0.1.0.dev2.dist-info/metadata.json
django_crypto_exchanges-0.1.0.dev2.dist-info/top_level.txt
